{
  "fio version" : "fio-3.17",
  "timestamp" : 1581499515,
  "timestamp_ms" : 1581499515880,
  "time" : "Wed Feb 12 01:25:15 2020",
  "jobs" : [
    {
      "jobname" : "wipc",
      "groupid" : 0,
      "error" : 0,
      "eta" : 0,
      "elapsed" : 891,
      "job options" : {
        "ioengine" : "libaio",
        "group_reporting" : "1",
        "direct" : "1",
        "rw" : "write",
        "bssplit" : "128KB",
        "numjobs" : "1",
        "iodepth" : "32",
        "size" : "75%",
        "io_size" : "256071352320B",
        "filename" : "/dev/sda"
      },
      "read" : {
        "io_bytes" : 0,
        "io_kbytes" : 0,
        "bw_bytes" : 0,
        "bw" : 0,
        "iops" : 0.000000,
        "runtime" : 0,
        "total_ios" : 0,
        "short_ios" : 0,
        "drop_ios" : 0,
        "slat_ns" : {
          "min" : 0,
          "max" : 0,
          "mean" : 0.000000,
          "stddev" : 0.000000
        },
        "clat_ns" : {
          "min" : 0,
          "max" : 0,
          "mean" : 0.000000,
          "stddev" : 0.000000,
          "percentile" : {
            "1.000000" : 0,
            "5.000000" : 0,
            "10.000000" : 0,
            "20.000000" : 0,
            "30.000000" : 0,
            "40.000000" : 0,
            "50.000000" : 0,
            "60.000000" : 0,
            "70.000000" : 0,
            "80.000000" : 0,
            "90.000000" : 0,
            "95.000000" : 0,
            "99.000000" : 0,
            "99.500000" : 0,
            "99.900000" : 0,
            "99.950000" : 0,
            "99.990000" : 0
          },
          "bins" : {

          }
        },
        "lat_ns" : {
          "min" : 0,
          "max" : 0,
          "mean" : 0.000000,
          "stddev" : 0.000000
        },
        "bw_min" : 0,
        "bw_max" : 0,
        "bw_agg" : 0.000000,
        "bw_mean" : 0.000000,
        "bw_dev" : 0.000000,
        "bw_samples" : 0,
        "iops_min" : 0,
        "iops_max" : 0,
        "iops_mean" : 0.000000,
        "iops_stddev" : 0.000000,
        "iops_samples" : 0
      },
      "write" : {
        "io_bytes" : 256071434240,
        "io_kbytes" : 250069760,
        "bw_bytes" : 287754337,
        "bw" : 281010,
        "iops" : 2195.391372,
        "runtime" : 889896,
        "total_ios" : 1953670,
        "short_ios" : 0,
        "drop_ios" : 0,
        "slat_ns" : {
          "min" : 8859,
          "max" : 506849,
          "mean" : 32899.410960,
          "stddev" : 10808.120777
        },
        "clat_ns" : {
          "min" : 1025561,
          "max" : 46739486,
          "mean" : 14536549.044841,
          "stddev" : 2015951.713042,
          "percentile" : {
            "1.000000" : 12648448,
            "5.000000" : 12910592,
            "10.000000" : 13172736,
            "20.000000" : 13434880,
            "30.000000" : 13565952,
            "40.000000" : 13828096,
            "50.000000" : 14090240,
            "60.000000" : 14483456,
            "70.000000" : 14876672,
            "80.000000" : 15269888,
            "90.000000" : 15925248,
            "95.000000" : 16580608,
            "99.000000" : 27394048,
            "99.500000" : 28180480,
            "99.900000" : 29491200,
            "99.950000" : 30015488,
            "99.990000" : 31850496
          },
          "bins" : {
            "1028096" : 1,
            "1073152" : 2,
            "1236992" : 1,
            "1417216" : 1,
            "1646592" : 1,
            "1761280" : 1,
            "1859584" : 1,
            "1990656" : 1,
            "2113536" : 1,
            "2342912" : 1,
            "2670592" : 1,
            "2736128" : 1,
            "3063808" : 2,
            "3129344" : 2,
            "3424256" : 1,
            "3489792" : 1,
            "3784704" : 1,
            "3817472" : 2,
            "4112384" : 1,
            "4177920" : 1,
            "4227072" : 1,
            "4489216" : 3,
            "4816896" : 1,
            "4882432" : 2,
            "5144576" : 1,
            "5210112" : 1,
            "5275648" : 1,
            "5472256" : 1,
            "5537792" : 2,
            "5865472" : 2,
            "5931008" : 1,
            "6127616" : 1,
            "6193152" : 1,
            "6258688" : 2,
            "6455296" : 1,
            "6586368" : 2,
            "6651904" : 1,
            "6782976" : 1,
            "7241728" : 1,
            "7503872" : 2,
            "7634944" : 1,
            "7766016" : 1,
            "7897088" : 1,
            "8454144" : 1,
            "8716288" : 1,
            "8847360" : 1,
            "9109504" : 2,
            "9502720" : 2,
            "9764864" : 1,
            "9895936" : 1,
            "10027008" : 1,
            "10420224" : 3,
            "10551296" : 1,
            "10682368" : 3,
            "10813440" : 5,
            "10944512" : 4,
            "11075584" : 3,
            "11206656" : 4,
            "11337728" : 3,
            "11468800" : 6,
            "11599872" : 4,
            "11730944" : 28,
            "11862016" : 83,
            "11993088" : 101,
            "12124160" : 184,
            "12255232" : 526,
            "12386304" : 1379,
            "12517376" : 5090,
            "12648448" : 14031,
            "12779520" : 29490,
            "12910592" : 53997,
            "13041664" : 78100,
            "13172736" : 95821,
            "13303808" : 104099,
            "13434880" : 105930,
            "13565952" : 105102,
            "13697024" : 106450,
            "13828096" : 107666,
            "13959168" : 101203,
            "14090240" : 93517,
            "14221312" : 83872,
            "14352384" : 74509,
            "14483456" : 68355,
            "14614528" : 66545,
            "14745600" : 63914,
            "14876672" : 58659,
            "15007744" : 50923,
            "15138816" : 46634,
            "15269888" : 47834,
            "15400960" : 50916,
            "15532032" : 51476,
            "15663104" : 46067,
            "15794176" : 37561,
            "15925248" : 29164,
            "16056320" : 22326,
            "16187392" : 17385,
            "16318464" : 14425,
            "16449536" : 13412,
            "16580608" : 13421,
            "16711680" : 12993,
            "16908288" : 20807,
            "17170432" : 12196,
            "17432576" : 6337,
            "17694720" : 3633,
            "17956864" : 1656,
            "18219008" : 1049,
            "18481152" : 851,
            "18743296" : 678,
            "19005440" : 471,
            "19267584" : 296,
            "19529728" : 129,
            "19791872" : 68,
            "20054016" : 43,
            "20316160" : 20,
            "20578304" : 11,
            "20840448" : 14,
            "21102592" : 58,
            "21364736" : 53,
            "21626880" : 19,
            "21889024" : 12,
            "22151168" : 6,
            "22413312" : 7,
            "22675456" : 25,
            "22937600" : 3,
            "23199744" : 5,
            "23461888" : 13,
            "23724032" : 21,
            "23986176" : 18,
            "24248320" : 8,
            "24510464" : 3,
            "24772608" : 5,
            "25034752" : 10,
            "25296896" : 26,
            "25559040" : 66,
            "25821184" : 164,
            "26083328" : 291,
            "26345472" : 744,
            "26607616" : 2636,
            "26869760" : 4195,
            "27131904" : 3945,
            "27394048" : 3216,
            "27656192" : 3231,
            "27918336" : 2780,
            "28180480" : 2445,
            "28442624" : 2102,
            "28704768" : 1777,
            "28966912" : 1281,
            "29229056" : 807,
            "29491200" : 562,
            "29753344" : 330,
            "30015488" : 325,
            "30277632" : 272,
            "30539776" : 176,
            "30801920" : 132,
            "31064064" : 76,
            "31326208" : 39,
            "31588352" : 33,
            "31850496" : 27,
            "32112640" : 14,
            "32374784" : 28,
            "32636928" : 2,
            "32899072" : 6,
            "33816576" : 3,
            "34340864" : 1,
            "40108032" : 1,
            "40632320" : 4,
            "41156608" : 4,
            "41680896" : 23,
            "42205184" : 22,
            "42729472" : 19,
            "43253760" : 13,
            "43778048" : 17,
            "44302336" : 11,
            "44826624" : 7,
            "46399488" : 1,
            "46923776" : 2
          }
        },
        "lat_ns" : {
          "min" : 1086715,
          "max" : 46757620,
          "mean" : 14570119.788095,
          "stddev" : 2015821.244785
        },
        "bw_min" : 252672,
        "bw_max" : 297216,
        "bw_agg" : 99.995492,
        "bw_mean" : 280997.331085,
        "bw_dev" : 6469.728644,
        "bw_samples" : 1779,
        "iops_min" : 1974,
        "iops_max" : 2322,
        "iops_mean" : 2195.274311,
        "iops_stddev" : 50.547687,
        "iops_samples" : 1779
      },
      "trim" : {
        "io_bytes" : 0,
        "io_kbytes" : 0,
        "bw_bytes" : 0,
        "bw" : 0,
        "iops" : 0.000000,
        "runtime" : 0,
        "total_ios" : 0,
        "short_ios" : 0,
        "drop_ios" : 0,
        "slat_ns" : {
          "min" : 0,
          "max" : 0,
          "mean" : 0.000000,
          "stddev" : 0.000000
        },
        "clat_ns" : {
          "min" : 0,
          "max" : 0,
          "mean" : 0.000000,
          "stddev" : 0.000000,
          "percentile" : {
            "1.000000" : 0,
            "5.000000" : 0,
            "10.000000" : 0,
            "20.000000" : 0,
            "30.000000" : 0,
            "40.000000" : 0,
            "50.000000" : 0,
            "60.000000" : 0,
            "70.000000" : 0,
            "80.000000" : 0,
            "90.000000" : 0,
            "95.000000" : 0,
            "99.000000" : 0,
            "99.500000" : 0,
            "99.900000" : 0,
            "99.950000" : 0,
            "99.990000" : 0
          },
          "bins" : {

          }
        },
        "lat_ns" : {
          "min" : 0,
          "max" : 0,
          "mean" : 0.000000,
          "stddev" : 0.000000
        },
        "bw_min" : 0,
        "bw_max" : 0,
        "bw_agg" : 0.000000,
        "bw_mean" : 0.000000,
        "bw_dev" : 0.000000,
        "bw_samples" : 0,
        "iops_min" : 0,
        "iops_max" : 0,
        "iops_mean" : 0.000000,
        "iops_stddev" : 0.000000,
        "iops_samples" : 0
      },
      "sync" : {
        "lat_ns" : {
          "min" : 0,
          "max" : 0,
          "mean" : 0.000000,
          "stddev" : 0.000000,
          "percentile" : {
            "1.000000" : 0,
            "5.000000" : 0,
            "10.000000" : 0,
            "20.000000" : 0,
            "30.000000" : 0,
            "40.000000" : 0,
            "50.000000" : 0,
            "60.000000" : 0,
            "70.000000" : 0,
            "80.000000" : 0,
            "90.000000" : 0,
            "95.000000" : 0,
            "99.000000" : 0,
            "99.500000" : 0,
            "99.900000" : 0,
            "99.950000" : 0,
            "99.990000" : 0
          },
          "bins" : {

          }
        },
        "total_ios" : 0
      },
      "job_runtime" : 889895,
      "usr_cpu" : 5.344338,
      "sys_cpu" : 12.810163,
      "ctx" : 1948490,
      "majf" : 0,
      "minf" : 23,
      "iodepth_level" : {
        "1" : 0.100000,
        "2" : 0.100000,
        "4" : 0.100000,
        "8" : 0.100000,
        "16" : 0.100000,
        "32" : 99.995240,
        ">=64" : 0.000000
      },
      "iodepth_submit" : {
        "0" : 0.000000,
        "4" : 100.000000,
        "8" : 0.000000,
        "16" : 0.000000,
        "32" : 0.000000,
        "64" : 0.000000,
        ">=64" : 0.000000
      },
      "iodepth_complete" : {
        "0" : 0.000000,
        "4" : 99.999846,
        "8" : 0.000000,
        "16" : 0.000000,
        "32" : 0.100000,
        "64" : 0.000000,
        ">=64" : 0.000000
      },
      "latency_ns" : {
        "2" : 0.000000,
        "4" : 0.000000,
        "10" : 0.000000,
        "20" : 0.000000,
        "50" : 0.000000,
        "100" : 0.000000,
        "250" : 0.000000,
        "500" : 0.000000,
        "750" : 0.000000,
        "1000" : 0.000000
      },
      "latency_us" : {
        "2" : 0.000000,
        "4" : 0.000000,
        "10" : 0.000000,
        "20" : 0.000000,
        "50" : 0.000000,
        "100" : 0.000000,
        "250" : 0.000000,
        "500" : 0.000000,
        "750" : 0.000000,
        "1000" : 0.000000
      },
      "latency_ms" : {
        "2" : 0.010000,
        "4" : 0.010000,
        "10" : 0.010000,
        "20" : 98.348595,
        "50" : 1.648129,
        "100" : 0.000000,
        "250" : 0.000000,
        "500" : 0.000000,
        "750" : 0.000000,
        "1000" : 0.000000,
        "2000" : 0.000000,
        ">=2000" : 0.000000
      },
      "latency_depth" : 32,
      "latency_target" : 0,
      "latency_percentile" : 100.000000,
      "latency_window" : 0
    }
  ],
  "disk_util" : [
    {
      "name" : "sda",
      "read_ios" : 76,
      "write_ios" : 1952709,
      "read_merges" : 0,
      "write_merges" : 916,
      "read_ticks" : 292,
      "write_ticks" : 28300248,
      "in_queue" : 28298656,
      "util" : 100.000000
    }
  ]
}
